stft/__init__.py
stft/stft.py
stft/types.py
stft/utils.py
stft-0.5.2.dist-info/DESCRIPTION.rst
stft-0.5.2.dist-info/METADATA
stft-0.5.2.dist-info/RECORD
stft-0.5.2.dist-info/WHEEL
stft-0.5.2.dist-info/metadata.json
stft-0.5.2.dist-info/top_level.txt
stft-0.5.2.dist-info/zip-safe
